candleweb_ai/__init__.py
candleweb_ai/tool.py
candleweb_ai-0.1.3.dist-info/LICENSE
candleweb_ai-0.1.3.dist-info/METADATA
candleweb_ai-0.1.3.dist-info/WHEEL
candleweb_ai-0.1.3.dist-info/top_level.txt
candleweb_ai-0.1.3.dist-info/RECORD
